airport_manager/__init__.py
airport_manager/cli.py
airport_manager/config.py
airport_manager/main_menu.py
airport_manager/utils.py
airport_manager/auth/__init__.py
airport_manager/auth/main_menu.py
airport_manager/auth/menu.py
airport_manager/auth/routes.py
airport_manager/data/Facts.py
airport_manager/data/__init__.py
airport_manager/database/__init__.py
airport_manager/database/main_menu.py
airport_manager/database/menu.py
airport_manager/database/routes.py
airport_manager/fa24/__init__.py
airport_manager/fa24/main_menu.py
airport_manager/fa24/menu.py
airport_manager/fa24/routes.py
airport_manager/flight_tracker_v1/__init__.py
airport_manager/flight_tracker_v1/main_menu.py
airport_manager/flight_tracker_v1/menu.py
airport_manager/flight_tracker_v1/routes.py
airport_manager/flight_tracker_v1/utils.py
animations/__init__.py
animations/banner.py
animations/end_animation.py
animations/welcome_animation.py
airport_manager-0.2.29.dist-info/METADATA
airport_manager-0.2.29.dist-info/WHEEL
airport_manager-0.2.29.dist-info/entry_points.txt
airport_manager-0.2.29.dist-info/top_level.txt
airport_manager-0.2.29.dist-info/RECORD
