Metadata-Version: 2.1
Name: airport-manager
Version: 0.2.29
Summary: Airport Manager: One-stop shop for all airport management needs.
Home-page: https://github.com/itsjustshubh/airport_manager
Author: Shubh Thorat
Author-email: reapers-arras.0y@icloud.com
Classifier: Programming Language :: Python :: 3
Classifier: License :: OSI Approved :: MIT License
Classifier: Operating System :: OS Independent
Requires-Python: >=3.6
Requires-Dist: requests
Requires-Dist: rich
Requires-Dist: click
Requires-Dist: python-dotenv
